{
    "chatbot": "dubi-OPP-bot-1",
    "performance_metrics": {
        "accuracy": 0.7485,
        "precision": 0.8182,
        "recall": 0.8936,
        "f1score": 0.8542
    },
    "dialog_metrics": {
        "tmR": 1.2681,
        "tf": 0.0994,
        "tc": 0.7143,
        "tcr": 0.7425,
        "tamb": 0.0994
    },
    "test_coverage": {
        "intents": 0.96,
        "dialog_nodes": 0.8298
    },
    "test_case": {
        "id": "68abddff-b3db-4813-8266-9c48bf6b82d3",
        "total_interactions": 171,
        "total_failed_interactions": 43,
        "failed_interactions": [
            {
                "id": "18f4a80a-46a9-499f-b09d-2670ec34d843",
                "type": 1,
                "binding_intent": "COMP_Agradecimento",
                "simulated_message": "Qual a definição de \"show de bola\"?",
                "expected_answer": "Continuo à disposição. Se não precisar mais de ajuda, por favor, <b>avalie o atendimento</b>. ('Gostei 👍 ', ':like:'), ('Não gostei 👎 ', ':dislike:')",
                "received_answer": "No momento não sei falar sobre isso. Vamos falar de outra coisa?",
                "response_time": 0.8307483196258545
            },
            {
                "id": "a75baf00-35af-45a1-a882-51f86b6f2eac",
                "type": 1,
                "binding_intent": "COMP_Agradecimento",
                "simulated_message": "Quais são os efeitos de um \"show de bola\"?",
                "expected_answer": "Continuo à disposição. Se não precisar mais de ajuda, por favor, <b>avalie o atendimento</b>. ('Gostei 👍 ', ':like:'), ('Não gostei 👎 ', ':dislike:')",
                "received_answer": "No momento não sei falar sobre isso. Vamos falar de outra coisa?",
                "response_time": 0.8984477519989014
            },
            {
                "id": "54ae7651-84a6-4b56-a373-a29326a619c9",
                "type": 2,
                "binding_intent": "COMP_Apresentacao",
                "simulated_message": "Como você se chama?",
                "expected_answer": "Olá, sou <b>Iara</b>, a <b>Assistente Virtual da Prefeitura de OPP</b>!\n\nPor enquanto, sei responder sobre <b>IPTU</b> e <b>alguns serviços de saúde</b>.",
                "received_answer": "('Apresentação', 'suggestion-watson|d:bab53d9c-911f-449d-b31c-b7f0ef088fa6'), ('Conteúdo', 'suggestion-watson|d:8db0cd2c-a961-43cd-b5e9-6c13a563d957'), ('Nenhuma das opções', 'suggestion-watson|d:1e8f7125-0b06-4a7e-b1f6-1f443a0a096c')",
                "response_time": 0.8194625377655029
            },
            {
                "id": "07eeb0ba-b41c-40b4-9c5f-8d82933b1b65",
                "type": 1,
                "binding_intent": "COMP_Encerramento",
                "simulated_message": "Quais são as formas de encerrar uma conversa?",
                "expected_answer": "OK. Peço que avalie o atendimento. Sua avaliação é muito importante para melhoria constante das minhas respostas.('Gostei 👍 ', ':like:'), ('Não gostei 👎 ', ':dislike:')",
                "received_answer": "No momento não sei falar sobre isso. Vamos falar de outra coisa?",
                "response_time": 0.8474805355072021
            },
            {
                "id": "2370f5db-e5ee-4a03-9a43-900d5f026d19",
                "type": 2,
                "binding_intent": "COMP_VoceNaoSabeDeNada",
                "simulated_message": "O que você sabe sobre o assunto?",
                "expected_answer": "Por enquanto, sei responder sobre <b>IPTU</b> e <b>alguns serviços de saúde</b>.",
                "received_answer": "('Conteúdo', 'suggestion-watson|d:e2a8a888-b7c9-4cc1-b118-40bd60596401'), ('Apresentação', 'suggestion-watson|d:f783ecbc-d730-46a7-a6cd-e83e93779ce3'), ('Nenhuma das opções', 'suggestion-watson|d:40eea5f3-b7ee-40ce-af43-170621028dff')",
                "response_time": 0.7253587245941162
            },
            {
                "id": "de37c588-ef80-4309-9b58-3ec011c4ee01",
                "type": 1,
                "binding_intent": "IPTU_CONTATO",
                "simulated_message": "Quero falar com um atendente sobre o IPTU",
                "expected_answer": "Se você deseja <b>contato humano</b> sobre <b>dúvidas</b> sobre <b>IPTU</b>, você pode: \n<ul><li>enviar mensagens <b>Whatsapp</b> para <b>(63) 99935-7789</b></li> \n<li><b><a target=\"_blank\" href=\"https://www.google.com/maps/place/R.+Ademar+Vicente+Ferreira,+1155+-+Lot.+Panorama,+Aragua%C3%ADna+-+TO,+77824-140/@-7.1892149,-48.2091763,17z/data=!3m1!4b1!4m5!3m4!1s0x92d90db075c4250b:0xaa5b0b1379b66fec!8m2!3d-7.1892149!4d-48.2091763\">Ir à Rua Ademar Vicente Ferreira, 1155 - Centro</a></li></ul>",
                "received_answer": "('Falar com Humano', 'suggestion-watson|d:557c9008-04ef-4e08-b7e5-02becdf922e6'), ('Contato IPTU', 'suggestion-watson|d:711e9e0c-3997-4503-97cf-da72a08ca82f'), ('Nenhuma das opções', 'suggestion-watson|d:b072ede5-6846-4180-9782-707b64b0ef93')",
                "response_time": 0.7904360294342041
            },
            {
                "id": "b8959a66-9465-4b1b-a70a-a52250fe9b6b",
                "type": 1,
                "binding_intent": "IPTU_DESCONTOS",
                "simulated_message": "Existe alguma forma de abater o valor do IPTU?",
                "expected_answer": "O desconto para <b>pagamento</b> do IPTU <b>à vista</b> até 28 de fevereiro é de <b>10%</b>. \n\nO pagamento <b>parcelado</b> pode ser em até 9 vezes, com descontos proporcionais: \n\n<b>7%</b> = 2 parcelas  \n<b>6%</b> = 3 parcelas  \n<b>5%</b> = 4 parcelas \n<b>4%</b> = 5 parcelas \n<b>3%</b> = 6 parcelas \n<b>2%</b> = 7 parcelas \n<b>1%</b> = 8 parcelas \n<b>0%</b> = 9 parcelas \n\nQuem pagou o <b>IPTU do ano anterior em dia</b>, tem <b>mais 10%</b> de desconto! ('Pessoais', 'OPT-descontos-pessoais'), ('Imóveis', 'OPT-descontos-imoveis'), ('Lotes ou terrenos', 'OPT-descontos-lotes-terrenos')",
                "received_answer": "('Descontos IPTU', 'suggestion-watson|d:904eaf7f-488d-4140-ae5d-f7ac887d5d82'), ('Valor venal', 'suggestion-watson|d:ac11bd21-467b-42f3-ba00-873464ae67f7'), ('Nenhuma das opções', 'suggestion-watson|d:e9ea69f0-ec79-40de-8037-1ee083463d21')",
                "response_time": 0.8347749710083008
            },
            {
                "id": "8cb3b92a-01ea-4699-92a4-e354396b33a7",
                "type": 2,
                "binding_intent": "IPTU_DESCONTOS",
                "simulated_message": "Quanto é o desconto do IPTU?",
                "expected_answer": "O desconto para <b>pagamento</b> do IPTU <b>à vista</b> até 28 de fevereiro é de <b>10%</b>. \n\nO pagamento <b>parcelado</b> pode ser em até 9 vezes, com descontos proporcionais: \n\n<b>7%</b> = 2 parcelas  \n<b>6%</b> = 3 parcelas  \n<b>5%</b> = 4 parcelas \n<b>4%</b> = 5 parcelas \n<b>3%</b> = 6 parcelas \n<b>2%</b> = 7 parcelas \n<b>1%</b> = 8 parcelas \n<b>0%</b> = 9 parcelas \n\nQuem pagou o <b>IPTU do ano anterior em dia</b>, tem <b>mais 10%</b> de desconto! ('Pessoais', 'OPT-descontos-pessoais'), ('Imóveis', 'OPT-descontos-imoveis'), ('Lotes ou terrenos', 'OPT-descontos-lotes-terrenos')",
                "received_answer": "Erro na requisição.",
                "response_time": 9.31870722770691
            },
            {
                "id": "f1f53cb1-fc5b-4e5e-bc32-8919afc05363",
                "type": 2,
                "binding_intent": "IPTU_DESCONTOS_IMOVEIS",
                "simulated_message": "É possível ter desconto no IPTU ao arborizar meu imóvel?",
                "expected_answer": "Para <b>imóvel</b>, você tem direito a desconto de: \n\n<b>50%</b><ul><li><b>Imóvel residencial</b> de <b>frente</b> para feira livre</b></li></ul>\n<b>10%</b><ul><li>Calçada com <b>acessibilidade</b></li><li><b>Imóvel</b> com mínimo de 20% da área total de <b>permeabilidade do solo</b></li><li><b>Imóvel comercial</b> com <b>recuo</b> igual ou superior a <b>5 metros</b></li></ul>\n<b>5%</b><ul><li>Sistema de <b>captação</b> de <b>água</b> da <b>chuva</b></li><li>Imóvel com sistema de <b>geração</b> de <b>energia elétrica</b> fotovoltaica</li><li>Imóvel com <b>arborização</b></li></ul>\n<b>100% no primeiro ano</b> após o término de <b>obra nova</b>, se devidamente <b>licenciada</b>.\n('Solicitação desconto', 'OPT-solicitacao-desconto')('Captação de Água', 'OPT-documentos-captacao-agua'), ('Geração de Energia', 'OPT-documentos-geracao-energia'), ('Arborização', 'OPT-documentos-arborizacao')('Outros descontos', 'OPT_descontos')",
                "received_answer": "('Descontos imóveis', 'suggestion-watson|d:8781c110-f8fb-4c49-a0c4-85ae886bda0e'), ('Arborização', 'suggestion-watson|d:4ac1c17c-b03c-4fd6-95f4-9bcbb74a1955'), ('Nenhuma das opções', 'suggestion-watson|d:1a02965e-e9a8-486c-a239-2498b94ad456')",
                "response_time": 0.8512983322143555
            },
            {
                "id": "77668bb1-7666-4f88-9f9b-d4e1f57ad9f8",
                "type": 1,
                "binding_intent": "IPTU_DESCONTOS_PESSOAIS",
                "simulated_message": "Quem pode receber desconto no IPTU?",
                "expected_answer": "Você tem direito a <b>descontos</b> no IPTU de: \n<ul><li><b>50%</b> - se possui <b>guarda provisória</b> de criança ou adolescente</li>\n<li><b>10%</b> - se possui <b>cadastro</b> imobiliário <b>atualizado</b></li> \n<li><b>2%</b> - se é <b>doador</b> de sangue ou medula</li></ul>('Solicitação desconto', 'OPT-solicitacao-deconto')('Doador de Sangue', 'OPT-documentos-doador-sangue'), ('Doador de Medula', 'OPT-documentos-doador-medula')('Outros descontos', 'OPT_descontos')",
                "received_answer": "('Descontos IPTU', 'suggestion-watson|d:7ecd1afb-2f2c-4c7e-9e1f-ebe2f171a0ff'), ('Apresentação', 'suggestion-watson|d:a818bb0a-a6fc-477d-b0d6-ea029216b67e'), ('Nenhuma das opções', 'suggestion-watson|d:3f7d474b-8598-4f9f-bcdf-5dbb7db6e928')",
                "response_time": 0.7922983169555664
            },
            {
                "id": "40a9e0ae-2f5c-4cc5-8fee-e804adcd8049",
                "type": 1,
                "binding_intent": "IPTU_DESCONTOS_PESSOAIS",
                "simulated_message": "Qual o benefício para o doador de sangue em relação ao IPTU?",
                "expected_answer": "Você tem direito a <b>descontos</b> no IPTU de: \n<ul><li><b>50%</b> - se possui <b>guarda provisória</b> de criança ou adolescente</li>\n<li><b>10%</b> - se possui <b>cadastro</b> imobiliário <b>atualizado</b></li> \n<li><b>2%</b> - se é <b>doador</b> de sangue ou medula</li></ul>('Solicitação desconto', 'OPT-solicitacao-deconto')('Doador de Sangue', 'OPT-documentos-doador-sangue'), ('Doador de Medula', 'OPT-documentos-doador-medula')('Outros descontos', 'OPT_descontos')",
                "received_answer": "No momento não sei falar sobre isso. Vamos falar de outra coisa?",
                "response_time": 1.1294310092926025
            },
            {
                "id": "b37867a2-9831-4ece-b1f2-a8575ec078b0",
                "type": 2,
                "binding_intent": "IPTU_DESCONTOS_PESSOAIS",
                "simulated_message": "Qual é o beneficio fiscal para dadores de medula e sangue?",
                "expected_answer": "Você tem direito a <b>descontos</b> no IPTU de: \n<ul><li><b>50%</b> - se possui <b>guarda provisória</b> de criança ou adolescente</li>\n<li><b>10%</b> - se possui <b>cadastro</b> imobiliário <b>atualizado</b></li> \n<li><b>2%</b> - se é <b>doador</b> de sangue ou medula</li></ul>('Solicitação desconto', 'OPT-solicitacao-deconto')('Doador de Sangue', 'OPT-documentos-doador-sangue'), ('Doador de Medula', 'OPT-documentos-doador-medula')('Outros descontos', 'OPT_descontos')",
                "received_answer": "No momento não sei falar sobre isso. Vamos falar de outra coisa?",
                "response_time": 1.0959763526916504
            },
            {
                "id": "c8e621f6-e7ee-43ca-b11c-bceef7c9500a",
                "type": 2,
                "binding_intent": "IPTU_DESCONTOS_TERRENOS",
                "simulated_message": "Como conseguir desconto na adesão de terrenos?",
                "expected_answer": "Para <b>lote ou terreno</b>, você tem direito a desconto de: \n\n<b>10%</b> - se possuir <b>fundos e laterais murados</b> e <b>frente com</b> grade, alambrado, mureta com no mínimo 1 metro de altura ou outro fechamento que possibilite fácil <b>visibilidade do interior</b>. \n\nAlém de mais <b>10%</b> se possuir <b>calçada com acessibilidade</b>.\n\nPela data de adesão, você tem direito a descontos para <b>pagamento</b> à vista ou parcelado: \n\n<b>35%</b> - até o último dia de <b>fevereiro</b> \n<b>20%</b> - até o último dia de <b>março</b> \n<b>10%</b> - até o último dia de <b>abril</b> \n('Solicitação desconto', 'OPT-solicitacao-desconto')('Outros descontos', 'OPT_descontos')",
                "received_answer": "('Lotes ou terrenos', 'suggestion-watson|d:a353791a-7d90-4f22-9234-ddd45fe0691b'), ('Solicitação', 'suggestion-watson|d:d3bd6d53-67a1-4d06-9ef8-4dae0b4763b1'), ('Nenhuma das opções', 'suggestion-watson|d:ca0f4f4d-feb6-4be2-8993-beec6ab27d48')",
                "response_time": 0.8043255805969238
            },
            {
                "id": "20d397bc-5efd-4148-9a8d-a67a35cd4e43",
                "type": 1,
                "binding_intent": "IPTU_DOCUMENTOS-ARBORIZACAO",
                "simulated_message": "Qual é a importância de um laudo de imóvel arborizado?",
                "expected_answer": "Os <b>documentos</b> necessários para obter o desconto do IPTU por <b>arborização</b> no imóvel são: \n<ol><li><b><a target=\"_blank\" href=\"https://OPP-bot-1.OPP.gov.br/portal/pdf/RequerimentoDescontoIPTUOPP-bot-1.pdf\">Formulário de Solicitação de Desconto</a></b></li>\n<li>Inscrição Imobiliária - <b>CCI</b> ou espelho do imóvel</li>\n<li>pessoas <b>físicas</b>: cópia do <b>documento</b> pessoal oficial <b>com foto</b> \n\npessoas <b>jurídicas</b>: cópia do <b>CNPJ</b>, respectivo <b>ato constitutivo</b> e do <b>documento</b> pessoal do <b>responsável lega</b>l</li>\n<li><b>fotografias coloridas e nítidas</b> de modo que possibilite analisar a <b>espécie arbórea</b> contida no imóvel, com as seguintes especificações: \n \n a) <b>data, hora, local e coordenadas geográficas</b>\n \n b) no mínimo <b>2 (duas) fotografias</b> amplas que abranjam a <b>árvore toda</b> \n \nc) no mínimo <b>1 (uma) fotografia</b> do <b>caule</b> da árvore ( <b>tronco</b> ) \n \nd) no mínimo <b>1 (uma) fotografia</b> da <b>copa</b> da árvore ( <b>galhos e folhagem</b> ).</li></ol>('Árvores', 'OPT-especies-arvores')",
                "received_answer": "No momento não sei falar sobre isso. Vamos falar de outra coisa?",
                "response_time": 0.8458008766174316
            },
            {
                "id": "1f278fac-8e20-46de-a1b1-69aae60d5863",
                "type": 1,
                "binding_intent": "IPTU_DOCUMENTOS-ENERGIA-FOTOVOLTAICA",
                "simulated_message": "Quais são os benefícios de possuir placas solares de energia?",
                "expected_answer": "Os <b>documentos</b> necessários para obter o desconto do IPTU por <b>geração de energia elétrica fotovoltaica</b> são: \n<ol><li><b><a target=\"_blank\" href=\"https://OPP-bot-1.OPP.gov.br/portal/pdf/RequerimentoDescontoIPTUOPP-bot-1.pdf\">Formulário de Solicitação de Desconto</a></b></li>\n<li>Inscrição Imobiliária - <b>CCI</b> ou <b>espelho</b> do imóvel</li>\n<li>pessoas <b>físicas</b>: cópia do <b>documento</b> pessoal oficial <b>com foto</b>\n\npessoas <b>jurídicas</b>: cópia do <b>CNPJ</b>, respectivo ato constitutivo e do <b>documento</b> pessoal do <b>responsável legal</b></li>\n<li>cópia da fatura atual da conta de energia elétrica contendo a <b>informação</b> de que a Unidade Consumidora do imóvel é <b>geradora de energia elétrica fotovoltaica</b>.</li></ol>",
                "received_answer": "('Geração de energia', 'suggestion-watson|d:58cfee54-d27b-4fcd-bfc1-3ba41f97e373'), ('Descontos imóveis', 'suggestion-watson|d:aef7f694-b779-4029-84c6-c3d813184b18'), ('Nenhuma das opções', 'suggestion-watson|d:743ce927-4b93-4b1f-bc23-24d43d716eb8')",
                "response_time": 0.8020672798156738
            },
            {
                "id": "bb2126a1-e564-445a-a2eb-4aa79af79515",
                "type": 2,
                "binding_intent": "IPTU_DOCUMENTOS-ENERGIA-FOTOVOLTAICA",
                "simulated_message": "Qual é a função de um gerador de enerrgia solar?",
                "expected_answer": "Os <b>documentos</b> necessários para obter o desconto do IPTU por <b>geração de energia elétrica fotovoltaica</b> são: \n<ol><li><b><a target=\"_blank\" href=\"https://OPP-bot-1.OPP.gov.br/portal/pdf/RequerimentoDescontoIPTUOPP-bot-1.pdf\">Formulário de Solicitação de Desconto</a></b></li>\n<li>Inscrição Imobiliária - <b>CCI</b> ou <b>espelho</b> do imóvel</li>\n<li>pessoas <b>físicas</b>: cópia do <b>documento</b> pessoal oficial <b>com foto</b>\n\npessoas <b>jurídicas</b>: cópia do <b>CNPJ</b>, respectivo ato constitutivo e do <b>documento</b> pessoal do <b>responsável legal</b></li>\n<li>cópia da fatura atual da conta de energia elétrica contendo a <b>informação</b> de que a Unidade Consumidora do imóvel é <b>geradora de energia elétrica fotovoltaica</b>.</li></ol>",
                "received_answer": "No momento não sei falar sobre isso. Vamos falar de outra coisa?",
                "response_time": 0.7637956142425537
            },
            {
                "id": "502c4d9b-6377-4cdb-ad25-ea2e03ba54b3",
                "type": 1,
                "binding_intent": "IPTU_ISENCAO",
                "simulated_message": "Quais são as regras de isenção do IPTU?",
                "expected_answer": "('Como solicitar?', 'OPT_solicitar-isencao'), ('Isenção IPTU apenas', 'OPT_isencao-iptu-apenas')",
                "received_answer": "('Isenção IPTU e lixo', 'suggestion-watson|d:cc9580fa-e862-4d9a-91ea-d06d83e41482'), ('Descontos pessoais', 'suggestion-watson|d:6ffbe6c8-01ec-4ec4-bfeb-f64ae46d020c'), ('Nenhuma das opções', 'suggestion-watson|d:4916b09e-0392-4839-b33b-2b1e35c3adaa')",
                "response_time": 0.9644157886505127
            },
            {
                "id": "1d7c2861-79a0-4758-bb54-908d24d666b9",
                "type": 1,
                "binding_intent": "IPTU_REQUERIMENTO-DESCONTO",
                "simulated_message": "Como obter um desconto no IPTU?",
                "expected_answer": "Acesse o <b><a target=\"_blank\" href=\"https://OPP-bot-1.OPP.gov.br/portal/pdf/RequerimentoDescontoIPTUOPP-bot-1.pdf\">Formulário de Solicitação de Desconto</a></b>.",
                "received_answer": "O desconto para <b>pagamento</b> do IPTU <b>à vista</b> até 28 de fevereiro é de <b>10%</b>. \n\nO pagamento <b>parcelado</b> pode ser em até 9 vezes, com descontos proporcionais: \n\n<b>7%</b> = 2 parcelas  \n<b>6%</b> = 3 parcelas  \n<b>5%</b> = 4 parcelas \n<b>4%</b> = 5 parcelas \n<b>3%</b> = 6 parcelas \n<b>2%</b> = 7 parcelas \n<b>1%</b> = 8 parcelas \n<b>0%</b> = 9 parcelas \n\nQuem pagou o <b>IPTU do ano anterior em dia</b>, tem <b>mais 10%</b> de desconto! ('Pessoais', 'OPT-descontos-pessoais'), ('Imóveis', 'OPT-descontos-imoveis'), ('Lotes ou terrenos', 'OPT-descontos-lotes-terrenos')",
                "response_time": 0.9010365009307861
            },
            {
                "id": "e43821e4-6fdf-4804-af60-1b533de4e7f8",
                "type": 1,
                "binding_intent": "IPTU_REQUERIMENTO-DESCONTO",
                "simulated_message": "Qual é o procedimento para solicitar um desconto no IPTU?",
                "expected_answer": "Acesse o <b><a target=\"_blank\" href=\"https://OPP-bot-1.OPP.gov.br/portal/pdf/RequerimentoDescontoIPTUOPP-bot-1.pdf\">Formulário de Solicitação de Desconto</a></b>.",
                "received_answer": "('Descontos IPTU', 'suggestion-watson|d:df45186a-6015-4d83-adbe-0ef0d989df62'), ('Solicitar isenção', 'suggestion-watson|d:c06e2872-9414-4113-924f-2da7a9565ed1'), ('Nenhuma das opções', 'suggestion-watson|d:a6a1400a-ed91-4681-8282-5620c2bc7758')",
                "response_time": 6.0037901401519775
            },
            {
                "id": "75b596b5-c517-48be-aaba-8d16b42220db",
                "type": 2,
                "binding_intent": "IPTU_REQUERIMENTO-DESCONTO",
                "simulated_message": "Qual é o formulário para desconto do IPTU?",
                "expected_answer": "Acesse o <b><a target=\"_blank\" href=\"https://OPP-bot-1.OPP.gov.br/portal/pdf/RequerimentoDescontoIPTUOPP-bot-1.pdf\">Formulário de Solicitação de Desconto</a></b>.",
                "received_answer": "('Descontos IPTU', 'suggestion-watson|d:9337d59b-5c77-45c7-859a-11ff3b9d5ab6'), ('Contato IPTU', 'suggestion-watson|d:78fd7058-699f-478e-87ce-799b6ad2b0fc'), ('Nenhuma das opções', 'suggestion-watson|d:916d9456-53d6-4fed-90f9-1923bbe3604f')",
                "response_time": 0.8240499496459961
            },
            {
                "id": "82684fb7-3b14-4b6b-b3be-fed3c41690b3",
                "type": 2,
                "binding_intent": "IPTU_REQUERIMENTO-DESCONTO",
                "simulated_message": "Onde posso encontrar o requerimento para desconto do IPTU?",
                "expected_answer": "Acesse o <b><a target=\"_blank\" href=\"https://OPP-bot-1.OPP.gov.br/portal/pdf/RequerimentoDescontoIPTUOPP-bot-1.pdf\">Formulário de Solicitação de Desconto</a></b>.",
                "received_answer": "No momento não sei falar sobre isso. Vamos falar de outra coisa?",
                "response_time": 0.8425610065460205
            },
            {
                "id": "8c5c4081-2f60-45cd-8ede-d8bfbf5d9654",
                "type": 2,
                "binding_intent": "IPTU_VALORIZACAO-DESVALORIZACAO",
                "simulated_message": "Qual é a alíquota de IPTU para valorisação?",
                "expected_answer": "Conforme a localização, tamanho do terreno não edificado, tempo de construção do imóvel edificado e situação fundiária, os imóveis terão fatores de valorização ou desvalorização do valor venal.  \n\nFatores de <b>desvalorização</b> (descontos sobre o valor venal dos imóveis de 10% a 90%):  \n<ul><li>em frente a cemitério ou presídio</li>\n<li>distante de até 200 metros da estação de tratamento de esgoto</li>\n<li>encravados ou de fundo</li>\n<li>que não possuam regularização fundiária</li>\n<li>que estejam situados em áreas alagadiças</li>\n<li>edificados em vias não pavimentadas</li></ul>\n<b>Valorização</b> do imóvel (acréscimo de 10% sobre o valor venal de terrenos): \n<ul><li>ser de esquina</li>\n<li>estar em frente a parque urbano ou praça</li></ul>\nÉ sobre este valor venal que incide a alíquota de IPTU conforme o zoneamento da cidade. ",
                "received_answer": "No momento não sei falar sobre isso. Vamos falar de outra coisa?",
                "response_time": 0.8267643451690674
            },
            {
                "id": "22e51d46-cce8-4e62-9cd0-891e2885a687",
                "type": 2,
                "binding_intent": "MENU_BOLSA-FAMILIA",
                "simulated_message": "Qual é o objetivo do Bolsa Família?",
                "expected_answer": "O <b>acompanhamento semestral  obrigatório</b> do Bolsa Família deve ser feito por: \n<ul><li>crianças de <b>até 7 anos</b> de idade</li><li><b>mulher</b> em <b>qualquer idade</b></li></ul>\nSão <b>duas vigências</b> no ano: \n<ul><li>primeira, de 1 de janeiro a 30 de junho</li><li>segunda, de 1 de julho a 30 de dezembro</li></ul>\nProcure uma UBS - <b>Unidade Básica de Saúde</b>, preferencialmente, a do setor de moradia do beneficiário. \n\nSerão atualizados peso, altura, Cartão de Vacina, e, se gestante, Cartão da Gestante. ",
                "received_answer": "No momento não sei falar sobre isso. Vamos falar de outra coisa?",
                "response_time": 0.9713904857635498
            },
            {
                "id": "32cfe7d2-6556-4e6b-a9af-ca8b77846fa0",
                "type": 2,
                "binding_intent": "MENU_BOLSA-FAMILIA",
                "simulated_message": "Quais são os benefícios oferecidos pelo programa Bolsa Família?",
                "expected_answer": "O <b>acompanhamento semestral  obrigatório</b> do Bolsa Família deve ser feito por: \n<ul><li>crianças de <b>até 7 anos</b> de idade</li><li><b>mulher</b> em <b>qualquer idade</b></li></ul>\nSão <b>duas vigências</b> no ano: \n<ul><li>primeira, de 1 de janeiro a 30 de junho</li><li>segunda, de 1 de julho a 30 de dezembro</li></ul>\nProcure uma UBS - <b>Unidade Básica de Saúde</b>, preferencialmente, a do setor de moradia do beneficiário. \n\nSerão atualizados peso, altura, Cartão de Vacina, e, se gestante, Cartão da Gestante. ",
                "received_answer": "('Bolsa Família', 'suggestion-watson|d:b55b2d13-6bab-4e34-9341-42bf63aca5b6'), ('Atenção básica', 'suggestion-watson|d:38acf868-fe4b-4963-91cb-5be49c824fa7'), ('Nenhuma das opções', 'suggestion-watson|d:288c0009-46d5-421a-aa29-ca2a26f923d9')",
                "response_time": 0.8262994289398193
            },
            {
                "id": "ba08b748-5381-4b3d-9966-8f186f54de32",
                "type": 1,
                "binding_intent": "MENU_IPTU",
                "simulated_message": "O que é IPTU?",
                "expected_answer": "('Isenção', 'OPT_isencao-iptu-taxa-lixo'), ('Descontos', 'OPT_descontos'), ('Emissão', 'OPT_emissao')",
                "received_answer": "No momento não sei falar sobre isso. Vamos falar de outra coisa?",
                "response_time": 0.8339712619781494
            },
            {
                "id": "c4356718-aeb4-4fb0-bd02-091cf4aeaf0f",
                "type": 2,
                "binding_intent": "MENU_IPTU",
                "simulated_message": "Qual é o significado de iptu?",
                "expected_answer": "('Isenção', 'OPT_isencao-iptu-taxa-lixo'), ('Descontos', 'OPT_descontos'), ('Emissão', 'OPT_emissao')",
                "received_answer": "No momento não sei falar sobre isso. Vamos falar de outra coisa?",
                "response_time": 0.8963291645050049
            },
            {
                "id": "4d3eae8c-63d2-4590-b6ef-296b5bcb1666",
                "type": 2,
                "binding_intent": "MENU_IPTU",
                "simulated_message": "Quais são os detalhes do imposto i p t u?",
                "expected_answer": "('Isenção', 'OPT_isencao-iptu-taxa-lixo'), ('Descontos', 'OPT_descontos'), ('Emissão', 'OPT_emissao')",
                "received_answer": "No momento não sei falar sobre isso. Vamos falar de outra coisa?",
                "response_time": 0.7938683032989502
            },
            {
                "id": "804ed320-8db4-4045-972b-6fbd1993679d",
                "type": 1,
                "binding_intent": "SAUDE_AGENDAMENTO-CONSULTAS",
                "simulated_message": "Qual é o procedimento para agendar uma consulta?",
                "expected_answer": "O Agendamento de <b>Consultas Médicas na UBS</b> – Unidade Básica de Saúde pode ser feito por telefone, com uma <b>ligação gratuita</b> para <b>0800 641 2200</b>. ",
                "received_answer": "No momento não sei falar sobre isso. Vamos falar de outra coisa?",
                "response_time": 0.7479336261749268
            },
            {
                "id": "1813d6e2-492e-448c-ae4f-2c6f7c53f6a5",
                "type": 1,
                "binding_intent": "SAUDE_AGENDAMENTO-CONSULTAS",
                "simulated_message": "Quais são as opções para realizar o agendamento de consultas?",
                "expected_answer": "O Agendamento de <b>Consultas Médicas na UBS</b> – Unidade Básica de Saúde pode ser feito por telefone, com uma <b>ligação gratuita</b> para <b>0800 641 2200</b>. ",
                "received_answer": "No momento não sei falar sobre isso. Vamos falar de outra coisa?",
                "response_time": 0.795943021774292
            },
            {
                "id": "246d86cf-800c-480a-8a99-d67ce6d2264d",
                "type": 1,
                "binding_intent": "SAUDE_ATENCAO-BASICA",
                "simulated_message": "Quais são os principais serviços oferecidos na atenção básica?",
                "expected_answer": "('Solicitação DIU', 'OPT-solicitacao-DIU'), ('Solicitação Implanon', 'OPT-solicitacao-implanon')",
                "received_answer": "('Saúde da mulher', 'OPT-saude-da-mulher'), ('Fórmulas infantis', 'OPT-formulas-infantis'), ('Fibromialgia', 'OPT-fibromialgia')",
                "response_time": 6.136559009552002
            },
            {
                "id": "32a9c997-0cde-4ea4-9202-35e46fdc3503",
                "type": 1,
                "binding_intent": "SAUDE_ATENCAO-BASICA",
                "simulated_message": "Quais são as principais atividades realizadas na atenção básica?",
                "expected_answer": "('Solicitação DIU', 'OPT-solicitacao-DIU'), ('Solicitação Implanon', 'OPT-solicitacao-implanon')",
                "received_answer": "('Saúde da mulher', 'OPT-saude-da-mulher'), ('Fórmulas infantis', 'OPT-formulas-infantis'), ('Fibromialgia', 'OPT-fibromialgia')",
                "response_time": 0.9227132797241211
            },
            {
                "id": "d142e5a3-b5da-46fe-aad0-89ffbf610802",
                "type": 2,
                "binding_intent": "SAUDE_ATENCAO-BASICA",
                "simulated_message": "Quais são os sreviços de atenção básica?",
                "expected_answer": "('Solicitação DIU', 'OPT-solicitacao-DIU'), ('Solicitação Implanon', 'OPT-solicitacao-implanon')",
                "received_answer": "('Saúde da mulher', 'OPT-saude-da-mulher'), ('Fórmulas infantis', 'OPT-formulas-infantis'), ('Fibromialgia', 'OPT-fibromialgia')",
                "response_time": 0.7746968269348145
            },
            {
                "id": "cbe7d387-3657-44ef-9d28-07567eabe34c",
                "type": 2,
                "binding_intent": "SAUDE_ATENCAO-BASICA",
                "simulated_message": "Quais são os servicos de atentry básica?",
                "expected_answer": "('Solicitação DIU', 'OPT-solicitacao-DIU'), ('Solicitação Implanon', 'OPT-solicitacao-implanon')",
                "received_answer": "('Saúde da mulher', 'OPT-saude-da-mulher'), ('Fórmulas infantis', 'OPT-formulas-infantis'), ('Fibromialgia', 'OPT-fibromialgia')",
                "response_time": 7.457864284515381
            },
            {
                "id": "f05d96f1-5dcc-49e7-a536-bbe552fd227e",
                "type": 2,
                "binding_intent": "SAUDE_ATENCAO-BASICA_SAUDE-DA-MULHER_IMPLANON",
                "simulated_message": "O que é o dispozitivo hormonal implanon?",
                "expected_answer": "Apenas na <b>UBS OPP Sul</b> ou na <b>UBS Raimundo Gomes</b> é realizada consulta de avaliação para inserção de Implanon, onde o médico solicitará exames para análise. \n\nO <b>agendamento da consulta</b> pode ser realizado pelo telefone <b>0800 641 2200</b>. ('O que é Implanon?', 'OPT-implanon')",
                "received_answer": "O <b>implante contraceptivo intradérmico</b> é um método contraceptivo hormonal (Etonogestrel), disponível de graça nas Unidades Básicas de Saúde. É inserido na parte interna do braço não dominante (aquele que não é usado para escrever) sob anestesia local, com eficácia superior a 99% e duração de 3 anos. Pode ser colocado desde a adolescência e retirado a qualquer momento na UBS, com retorno imediato da fertilidade.",
                "response_time": 0.8467676639556885
            },
            {
                "id": "19f9a71a-bc87-4ef1-8b46-99c92da99939",
                "type": 1,
                "binding_intent": "SAUDE_ENDERECO-SECRETARIA-SAUDE",
                "simulated_message": "Qual é o endereço da Secretaria Municipal de Saúde?",
                "expected_answer": "<b>Secretaria Municipal de Saúde</b>\n\n<a target=\"_blank\" href=\"https://goo.gl/maps/taK7r6tAxPp8SdSM6\">Rua 07 de Setembro, 555, Centro, OPP - TO</a>",
                "received_answer": "('Secretaria Saúde', 'suggestion-watson|d:208c52fc-1ec5-4934-a67d-95e0e6bc4873'), ('Contato IPTU', 'suggestion-watson|d:2f8b0787-5aa4-4074-9dc5-8949d83970dc'), ('Nenhuma das opções', 'suggestion-watson|d:d34e19c3-137a-4cac-8dab-208f51e5a8a2')",
                "response_time": 0.809138298034668
            },
            {
                "id": "d960459e-980d-4807-968a-fa82f17d3893",
                "type": 2,
                "binding_intent": "SAUDE_ENDERECO-SECRETARIA-SAUDE",
                "simulated_message": "Qual é o enderesso da Secretaria Municipal de Saúde?",
                "expected_answer": "<b>Secretaria Municipal de Saúde</b>\n\n<a target=\"_blank\" href=\"https://goo.gl/maps/taK7r6tAxPp8SdSM6\">Rua 07 de Setembro, 555, Centro, OPP - TO</a>",
                "received_answer": "('Secretaria Saúde', 'suggestion-watson|d:d8f3e02c-10fd-437f-a1e8-2c2f5397d5a9'), ('Contato IPTU', 'suggestion-watson|d:83f8bd98-b988-4a7d-b075-397f4d74a24e'), ('Nenhuma das opções', 'suggestion-watson|d:7a061d35-f719-4209-bca3-66757be75e08')",
                "response_time": 0.9227044582366943
            },
            {
                "id": "d03dde72-5f14-4f38-a1d8-7289050bbb93",
                "type": 2,
                "binding_intent": "SAUDE_ENDERECO-SECRETARIA-SAUDE",
                "simulated_message": "O que é a Secretária de Saúde?",
                "expected_answer": "<b>Secretaria Municipal de Saúde</b>\n\n<a target=\"_blank\" href=\"https://goo.gl/maps/taK7r6tAxPp8SdSM6\">Rua 07 de Setembro, 555, Centro, OPP - TO</a>",
                "received_answer": "('Secretaria Saúde', 'suggestion-watson|d:a1d7b81e-2727-4c41-88f9-c1e40e8c10c5'), ('Saúde', 'suggestion-watson|d:5c1e3e38-242c-4354-9616-13a57f236a3f'), ('Nenhuma das opções', 'suggestion-watson|d:6e875c4b-3395-415d-84a0-d5d762095151')",
                "response_time": 0.805351972579956
            },
            {
                "id": "6f0612fa-37a9-48cb-aa9e-72441bbb8cd6",
                "type": 1,
                "binding_intent": "SAUDE_TFD-PASSAGENS",
                "simulated_message": "Como solicitar uma passagem para consulta médica?",
                "expected_answer": "O pedido de <b>passagens</b> para <b>dentro</b> do estado do <b>OPP</b> deve ser feito <b>presencialmente</b> na <a target=\"_blank\" href=\"https://goo.gl/maps/ugdvg9KSo5CsPGCB9\">Central de Regulação Municipal</a> em <b>até 10 (dez) dias úteis antes</b> da data do atendimento.\n\nVocê precisa entregar <b>2 (duas) cópias</b> dos seguintes documentos: \n<ul><li><b>Agendamento da consulta</b> com identificação da Unidade de Tratamento</li>\n<li><b>CPF</b>, <b>RG</b> (CNH/CDN) e <b>cartão do SUS</b> do paciente</li> \n<li><b>Comprovante de residência</b> do mês atual</li> \n<li>Se precisar de acompanhante, <b>CPF</b>, <b>RG</b> e <b>cartão do SUS</b> do acompanhante</li></ul>('Regulação Municipal', 'OPT-endereco-central-regulacao-municipal'), ('Outro estado', 'OPT-outro-estado')",
                "received_answer": "('OPP ', 'OPT-OPP'), ('Outro estado', 'OPT-outro-estado')",
                "response_time": 1.1306824684143066
            },
            {
                "id": "406c98c0-3e9d-459e-a14b-b79d2bf3198e",
                "type": 2,
                "binding_intent": "SAUDE_TFD-PASSAGENS",
                "simulated_message": "Qual a forma de adquirir uma passagem para consulta médica?",
                "expected_answer": "O pedido de <b>passagens</b> para <b>dentro</b> do estado do <b>OPP</b> deve ser feito <b>presencialmente</b> na <a target=\"_blank\" href=\"https://goo.gl/maps/ugdvg9KSo5CsPGCB9\">Central de Regulação Municipal</a> em <b>até 10 (dez) dias úteis antes</b> da data do atendimento.\n\nVocê precisa entregar <b>2 (duas) cópias</b> dos seguintes documentos: \n<ul><li><b>Agendamento da consulta</b> com identificação da Unidade de Tratamento</li>\n<li><b>CPF</b>, <b>RG</b> (CNH/CDN) e <b>cartão do SUS</b> do paciente</li> \n<li><b>Comprovante de residência</b> do mês atual</li> \n<li>Se precisar de acompanhante, <b>CPF</b>, <b>RG</b> e <b>cartão do SUS</b> do acompanhante</li></ul>('Regulação Municipal', 'OPT-endereco-central-regulacao-municipal'), ('Outro estado', 'OPT-outro-estado')",
                "received_answer": "('OPP ', 'OPT-OPP'), ('Outro estado', 'OPT-outro-estado')",
                "response_time": 0.8125576972961426
            },
            {
                "id": "09937536-3861-42b4-b9a0-e21df4591326",
                "type": 2,
                "binding_intent": "SAUDE_TFD-PASSAGENS",
                "simulated_message": "É possível solicitar uma doação de passagem?",
                "expected_answer": "O pedido de <b>passagens</b> para <b>dentro</b> do estado do <b>OPP</b> deve ser feito <b>presencialmente</b> na <a target=\"_blank\" href=\"https://goo.gl/maps/ugdvg9KSo5CsPGCB9\">Central de Regulação Municipal</a> em <b>até 10 (dez) dias úteis antes</b> da data do atendimento.\n\nVocê precisa entregar <b>2 (duas) cópias</b> dos seguintes documentos: \n<ul><li><b>Agendamento da consulta</b> com identificação da Unidade de Tratamento</li>\n<li><b>CPF</b>, <b>RG</b> (CNH/CDN) e <b>cartão do SUS</b> do paciente</li> \n<li><b>Comprovante de residência</b> do mês atual</li> \n<li>Se precisar de acompanhante, <b>CPF</b>, <b>RG</b> e <b>cartão do SUS</b> do acompanhante</li></ul>('Regulação Municipal', 'OPT-endereco-central-regulacao-municipal'), ('Outro estado', 'OPT-outro-estado')",
                "received_answer": "('OPP ', 'OPT-OPP'), ('Outro estado', 'OPT-outro-estado')",
                "response_time": 0.832740068435669
            },
            {
                "id": "eb7da8d2-0034-4445-9a9e-17497d0ff87d",
                "type": 2,
                "binding_intent": "SAUDE_TFD-PASSAGENS",
                "simulated_message": "Como posso obter uma passagem para tratamento de saude?",
                "expected_answer": "O pedido de <b>passagens</b> para <b>dentro</b> do estado do <b>OPP</b> deve ser feito <b>presencialmente</b> na <a target=\"_blank\" href=\"https://goo.gl/maps/ugdvg9KSo5CsPGCB9\">Central de Regulação Municipal</a> em <b>até 10 (dez) dias úteis antes</b> da data do atendimento.\n\nVocê precisa entregar <b>2 (duas) cópias</b> dos seguintes documentos: \n<ul><li><b>Agendamento da consulta</b> com identificação da Unidade de Tratamento</li>\n<li><b>CPF</b>, <b>RG</b> (CNH/CDN) e <b>cartão do SUS</b> do paciente</li> \n<li><b>Comprovante de residência</b> do mês atual</li> \n<li>Se precisar de acompanhante, <b>CPF</b>, <b>RG</b> e <b>cartão do SUS</b> do acompanhante</li></ul>('Regulação Municipal', 'OPT-endereco-central-regulacao-municipal'), ('Outro estado', 'OPT-outro-estado')",
                "received_answer": "('OPP ', 'OPT-OPP'), ('Outro estado', 'OPT-outro-estado')",
                "response_time": 7.290839433670044
            },
            {
                "id": "7f9af723-ce88-4103-bcd5-421b34ae0205",
                "type": 2,
                "binding_intent": "VOCABULARIO_DIU",
                "simulated_message": "Defina o que é o diu.",
                "expected_answer": "O <b>dispositivo intrauterino</b> (DIU) de cobre é um método contraceptivo não-hormonal e disponível de graça nas Unidades Básicas de Saúde, inserido dentro do útero sob anestesia local, com eficácia superior a 99% e duração de 10 anos. Pode ser colocado desde a adolescência e retirado a qualquer momento na UBS, com retorno imediato da fertilidade.",
                "received_answer": "('O que é DIU', 'suggestion-watson|d:bbae4945-574d-4226-89fd-43de7d6e77ed'), ('O que é Implanon', 'suggestion-watson|d:3bbeeb96-60fc-4e3a-983a-80b6e6326ef2'), ('Nenhuma das opções', 'suggestion-watson|d:d34e1270-9518-4d0b-abd6-70aaffe836f5')",
                "response_time": 0.9366433620452881
            },
            {
                "id": "144adc01-2d40-4b9c-9d5c-694d870cb690",
                "type": 2,
                "binding_intent": "VOCABULARIO_IMPLANON",
                "simulated_message": "Defina emplann",
                "expected_answer": "O <b>implante contraceptivo intradérmico</b> é um método contraceptivo hormonal (Etonogestrel), disponível de graça nas Unidades Básicas de Saúde. É inserido na parte interna do braço não dominante (aquele que não é usado para escrever) sob anestesia local, com eficácia superior a 99% e duração de 3 anos. Pode ser colocado desde a adolescência e retirado a qualquer momento na UBS, com retorno imediato da fertilidade.",
                "received_answer": "('O que é Implanon', 'suggestion-watson|d:5205ae8c-a119-4993-b1f9-3fb60b333a82'), ('O que é DIU', 'suggestion-watson|d:5851ad8c-82f9-4eb2-9d5a-79b7b605246d'), ('Nenhuma das opções', 'suggestion-watson|d:bee6ccfb-855b-4be6-aa8a-4a5f5841239f')",
                "response_time": 0.9228556156158447
            }
        ]
    }
}